snaky/__init__.py
snaky/enums.py
snaky/snake.py
snaky/snaky_contoller.py
snaky-0.0.1.dist-info/LICENSE
snaky-0.0.1.dist-info/METADATA
snaky-0.0.1.dist-info/WHEEL
snaky-0.0.1.dist-info/top_level.txt
snaky-0.0.1.dist-info/RECORD
