Metadata-Version: 2.1
Name: snaky
Version: 0.0.1
Summary: Yet another snake game implementation
Home-page: https://github.com/pypa/sampleproject
Author: pjsousa
Author-email: pjgs.sousa@gmail.com
License: UNKNOWN
Platform: UNKNOWN
Classifier: Programming Language :: Python :: 3
Classifier: License :: OSI Approved :: MIT License
Classifier: Operating System :: OS Independent
Requires-Python: >=3.6
License-File: LICENSE
